dynamaxsys/__init__.py
dynamaxsys/base.py
dynamaxsys/integrators.py
dynamaxsys/simplecar.py
dynamaxsys/test.py
dynamaxsys/test_integrators.py
dynamaxsys/unicycle.py
dynamaxsys/utils.py
dynamaxsys-0.0.7.dist-info/METADATA
dynamaxsys-0.0.7.dist-info/WHEEL
dynamaxsys-0.0.7.dist-info/top_level.txt
dynamaxsys-0.0.7.dist-info/RECORD
