Metadata-Version: 2.4
Name: dynamaxsys
Version: 0.0.7
Summary: dynamical systems with jax
Author-email: Karen Leung <kymleung@uw.edu>
Requires-Dist: jax
Requires-Dist: numpy
Requires-Dist: equinox
